odoo9_addon_donation_direct_debit-9.0.1.0.0-py2.7-nspkg.pth
odoo_addons/donation_direct_debit/__openerp__.py
odoo_addons/donation_direct_debit/donation_demo.xml
odoo_addons/donation_direct_debit/donation_view.xml
odoo_addons/donation_direct_debit/__init__.py
odoo_addons/donation_direct_debit/README.rst
odoo_addons/donation_direct_debit/donation.py
odoo_addons/donation_direct_debit/security/ir.model.access.csv
odoo_addons/donation_direct_debit/i18n/donation_direct_debit.pot
odoo_addons/donation_direct_debit/i18n/fr.po
odoo_addons/donation_direct_debit/tests/__init__.py
odoo_addons/donation_direct_debit/tests/test_direct_debit.py
odoo_addons/donation_direct_debit/static/description/icon.png
odoo9_addon_donation_direct_debit-9.0.1.0.0.dist-info/top_level.txt
odoo9_addon_donation_direct_debit-9.0.1.0.0.dist-info/WHEEL
odoo9_addon_donation_direct_debit-9.0.1.0.0.dist-info/RECORD
odoo9_addon_donation_direct_debit-9.0.1.0.0.dist-info/metadata.json
odoo9_addon_donation_direct_debit-9.0.1.0.0.dist-info/DESCRIPTION.rst
odoo9_addon_donation_direct_debit-9.0.1.0.0.dist-info/METADATA
odoo9_addon_donation_direct_debit-9.0.1.0.0.dist-info/namespace_packages.txt
