Metadata-Version: 2.0
Name: odoo9-addon-donation-direct-debit
Version: 9.0.1.0.0
Summary: Auto-generate direct debit order on donation validation
Home-page: http://www.akretion.com
Author: UNKNOWN
Author-email: UNKNOWN
License: AGPL-3
Platform: UNKNOWN
Requires-Dist: odoo (<9.1a,>=9.0a)
Requires-Dist: odoo9-addon-account-banking-sepa-direct-debit
Requires-Dist: odoo9-addon-donation
Classifier: Programming Language :: Python :: 2.7
Classifier: Framework :: Odoo
Classifier: License :: OSI Approved :: GNU Affero General Public License v3
